githubinformation/__init__.py
githubinformation/release.py
githubinformation/repo.py
githubinformation/update.py
githubinformation/user.py
githubinformation-1.0.dist-info/LICENSE
githubinformation-1.0.dist-info/METADATA
githubinformation-1.0.dist-info/WHEEL
githubinformation-1.0.dist-info/top_level.txt
githubinformation-1.0.dist-info/RECORD
