Metadata-Version: 2.1
Name: githubinformation
Version: 1.0
Summary: A tool that lets you check your GitHub Project for updates.
Home-page: https://github.com/wfxey/githubinformation
Download-URL: https://github.com/wfxey/githubinformation/archive/refs/tags/v1.0.tar.gz
Author: wfxey
Author-email: projectsdi02@gmail.com
License: MIT
Keywords: updates,github,check-for-updates
Classifier: Development Status :: 5 - Production/Stable
Classifier: Intended Audience :: Developers
Classifier: Topic :: Software Development :: Libraries
Classifier: License :: OSI Approved :: MIT License
Classifier: Programming Language :: Python :: 3.9
Requires-Python: >=3.9
License-File: LICENSE
Requires-Dist: requests
Requires-Dist: packaging
